cnx_query_grammar-0.2.2.dist-info/DESCRIPTION.rst
cnx_query_grammar-0.2.2.dist-info/METADATA
cnx_query_grammar-0.2.2.dist-info/RECORD
cnx_query_grammar-0.2.2.dist-info/WHEEL
cnx_query_grammar-0.2.2.dist-info/entry_points.txt
cnx_query_grammar-0.2.2.dist-info/metadata.json
cnx_query_grammar-0.2.2.dist-info/top_level.txt
cnxquerygrammar/__init__.py
cnxquerygrammar/query.peg
cnxquerygrammar/query_parser.py
cnxquerygrammar/tests.py
