Metadata-Version: 2.0
Name: cnx-query-grammar
Version: 0.2.2
Summary: Connexions project search query parsing library.
Home-page: https://github.com/connexions/cnx-query-grammar
Author: Connexions team
Author-email: info@cnx.org
License: AGPL, See also LICENSE.txt
Platform: UNKNOWN
Requires-Dist: parsimonious
